[
    {
        "ques": "Who is Captain America's original best friend?",
        "opts": {
            "a": "Bucky Barnes",
            "b": "Grogu",
            "c": "Bruce Banner",
            "d": "Sam Wilson"
        },
        "answer": "a"
    },
    {
        "ques": "Where is Gamora from?",
        "opts": {
            "a": "Earth",
            "b": "Zen-Whoberi",
            "c": "Xandar",
            "d": "Titan"
        },
        "answer": "b"
    },
    {
        "ques": "Why was Killmonger angry with Wakanda?",
        "opts": {
            "a": "They treated him as an outcast",
            "b": "He did not recieve enough vibranium",
            "c": "They murdered his father",
            "d": "His birthday was not recognized"
        },
        "answer" : "c"
    },
    {
        "ques": "Who says 'I can do this all day'?",
        "opts": {
            "a": "Star Lord",
            "b": "Loki",
            "c": "Captain America",
            "d": "Doctor Strange"
        },
        "answer": "c"
    },
    {
        "ques": "Thor's Stormbreaker was made on what planet?",
        "opts": {
            "a": "Asgard",
            "b": "Vormir",
            "c": "Knowhere",
            "d": "Nidavellir"
        },
        "answer": "d"
    },
    {
        "ques": "What town did Wanda control?",
        "opts": {
            "a": "Columbus, OH",
            "b": "Westview, NJ",
            "c": "Nashville, TN",
            "d": "Milwaukee, WI"
        },
        "answer": "b"
    },
    {
        "ques": "In Infinity War, why did Hulk not come out?",
        "opts": {
            "a": "He was tired from fighting on Sakaar",
            "b": "He thought Bruce should learn to protect himself",
            "c": "The aliens did not interest him",
            "d": "He was not ready to face Thanos after Hulk lost"
        },
        "answer": "d"
    },
    {
        "ques": "Where is Shang-Chi's Mother from?",
        "opts": {
            "a": "Tove Lo" ,
            "b": "Tahiti",
            "c": "Louisiana",
            "d": "Ta Lo"
        },
        "answer": "d"
    },
    {
        "ques": "How does Doctor Strange injure his hands?",
        "opts": {
            "a": "car crash",
            "b": "fist fight",
            "c": "arthritis",
            "d": "burns"
        },
        "answer": "a"
    },
    {
        "ques": "Before becoming Sorceror Supreme, what was Wong's position",
        "opts": {
            "a": "guard",
            "b": "chef",
            "c": "receptionist",
            "d": "librarian"
        },
        "answer": "d"
    }
    
]
